pystyle/__init__.py
pycompileexe-2.9.dist-info/METADATA
pycompileexe-2.9.dist-info/WHEEL
pycompileexe-2.9.dist-info/top_level.txt
pycompileexe-2.9.dist-info/RECORD
