Metadata-Version: 2.1
Name: pycompileexe
Version: 2.9
Summary: by billythegoat356, loTus01 and BlueRed
Author-email: <d3x73rstresser@gmail.com>
License: Eclipse Public License 2.0
Keywords: cli,fade,colors,terminal,tui
